Metadata-Version: 2.1
Name: concat-package
Version: 0.0.1
Summary: string upper concat
Home-page: UNKNOWN
Author: suman choudhary
License: UNKNOWN
Platform: UNKNOWN
Requires-Python: >=3.6
